README.md
setup.cfg
setup.py
converter_package/Action.py
converter_package/ActionModel.py
converter_package/CloudFramework.py
converter_package/ComputeNode.py
converter_package/Container.py
converter_package/Converter.py
converter_package/Image.py
converter_package/Kafka_Producer.py
converter_package/MatchingModel.py
converter_package/Parser.py
converter_package/Repository.py
converter_package/WorkflowModel.py
converter_package/Workflows.py
converter_package/__init__.py
converter_package.egg-info/PKG-INFO
converter_package.egg-info/SOURCES.txt
converter_package.egg-info/dependency_links.txt
converter_package.egg-info/not-zip-safe
converter_package.egg-info/requires.txt
converter_package.egg-info/top_level.txt