Metadata-Version: 2.1
Name: converter-package
Version: 0.5
Summary: This converter library is able to transform the ACCORDION application model to K3s configuration files
Home-page: UNKNOWN
Author: Giannis Korontanis
Author-email: gkorod2@gmail.com
License: MIT
Platform: UNKNOWN
